django_2fa/__init__.py
django_2fa/admin.py
django_2fa/apps.py
django_2fa/decorators.py
django_2fa/forms.py
django_2fa/middleware.py
django_2fa/migrations/0001_initial.py
django_2fa/migrations/0002_alter_device_unique_together.py
django_2fa/migrations/0003_device_setup_complete.py
django_2fa/migrations/0004_device_counter_expire.py
django_2fa/migrations/0005_mfarequest.py
django_2fa/migrations/0006_mfarequest_used.py
django_2fa/migrations/__init__.py
django_2fa/models.py
django_2fa/settings.py
django_2fa/static/2fa/2fa-icon.png
django_2fa/static/2fa/axios.min.js
django_2fa/static/2fa/cbor.js
django_2fa/static/2fa/qrious.min.js
django_2fa/templates/2fa/add-device.html
django_2fa/templates/2fa/base.html
django_2fa/templates/2fa/complete-fido.html
django_2fa/templates/2fa/devices.html
django_2fa/templates/2fa/email-code.html
django_2fa/templates/2fa/email-code.txt
django_2fa/templates/2fa/login.html
django_2fa/templates/2fa/request-completed.html
django_2fa/templates/2fa/verify-fido.html
django_2fa/templates/2fa/verify.html
django_2fa/tests.py
django_2fa/urls.py
django_2fa/views.py
django_2fa/views_api.py
django_2fa-0.9.0.dist-info/WHEEL
django_2fa-0.9.0.dist-info/METADATA
django_2fa-0.9.0.dist-info/LICENSE
django_2fa-0.9.0.dist-info/RECORD
